{
    "allowEntity": false,
    "collectionURIs": [
        "/afw/_AdaptiveCollection_/core"
    ],
    "description": "Adaptive Framework configuration component for type=adaptor adaptorType=model.",
    "objectType": "_AdaptiveConf_adaptor_model",
    "propertyTypes": {
        "_meta_": {
            "label": "Meta",
            "parentPaths": [
                "/afw/_AdaptiveObjectType_/_AdaptiveConf_adaptor/propertyTypes"
            ]
        },
        "custom": {
            "allowQuery": true,
            "brief": "Qualifier custom:: variables available to model expressions",
            "dataType": "object",
            "dataTypeParameter": "_AdaptiveTemplateProperties_",
            "description": "Qualifier custom:: variables available to model expressions.",
            "label": "Custom"
        },
        "mappedAdaptorId": {
            "allowQuery": true,
            "brief": "This is the default mappedAdaptorId value",
            "dataType": "template",
            "description": "This is the default mappedAdaptorId value.",
            "label": "Mapped Adaptor",
            "required": true
        },
        "modelId": {
            "allowQuery": true,
            "brief": "The objectId of the _AdaptiveModel_ object in the modelLocationAdaptorId adaptor",
            "dataType": "template",
            "description": "The objectId of the _AdaptiveModel_ object in the modelLocationAdaptorId adaptor.",
            "label": "Model",
            "required": true
        },
        "modelLocationAdaptorId": {
            "allowQuery": true,
            "brief": "This is the id of the adaptor that contains object type _AdaptiveModel_ and related objects",
            "dataType": "template",
            "description": "This is the id of the adaptor that contains object type _AdaptiveModel_ and related objects.",
            "label": "Model Adaptor",
            "required": true
        }
    }
}
